cnlp/__init__.py
cnlp/data/README.md
cnlp/data/__init__.py
cnlp/data/utils.py
cnlp/data/vocabulary.py
cnlp/data/vocabulary_test.py
cnlp/data/word_dict.py
cnlp/data/tokenizers/README.md
cnlp/data/tokenizers/__init__.py
cnlp/data/tokenizers/dag.py
cnlp/data/tokenizers/mechanical.py
cnlp/data/tokenizers/tokenizer.py
cnlp/data/tokenizers/tokenizer_test.py
cnlp/dataset/README.md
cnlp/dataset/__init__.py
cnlp/model/README.md
cnlp/model/__init__.py
cnlp/src/char_vocab.txt
cnlp/src/radical_dict.txt
cnlp/src/radical_vocab.txt
cnlp/src/stroke_dict.txt
cnlp/src/stroke_vocab.txt
cnlp/src/word_dict.txt
cnlp/src/word_vocab.txt
cnlp-0.1.0.dist-info/LICENSE
cnlp-0.1.0.dist-info/METADATA
cnlp-0.1.0.dist-info/WHEEL
cnlp-0.1.0.dist-info/top_level.txt
cnlp-0.1.0.dist-info/zip-safe
cnlp-0.1.0.dist-info/RECORD
