Metadata-Version: 2.1
Name: cnlp
Version: 0.1.0
Summary: A natural language processing framework focused on Chinese.
Home-page: https://github.com/dovolopor-research/cnlp
Author: Ailln
Author-email: kinggreenhall@gmail.com
License: MIT License
Platform: UNKNOWN
Classifier: Programming Language :: Python :: 3.6
Classifier: Programming Language :: Python :: 3.7
Classifier: Programming Language :: Python :: 3.8
Classifier: License :: OSI Approved :: MIT License
Classifier: Operating System :: OS Independent
Requires-Dist: numpy (>=1.15.0)
Requires-Dist: PyYAML (>=3.13)
